sqlite_s3vfs.py
sqlite_s3vfs-0.0.36.dist-info/METADATA
sqlite_s3vfs-0.0.36.dist-info/WHEEL
sqlite_s3vfs-0.0.36.dist-info/licenses/LICENSE
sqlite_s3vfs-0.0.36.dist-info/RECORD
