Metadata-Version: 2.1
Name: sqlite-s3vfs
Version: 0.0.36
Summary: Virtual filesystem for SQLite to read from and write to S3
Project-URL: Homepage, https://github.com/uktrade/sqlite-s3vfs
Author-email: Department for International Trade <sre@digital.trade.gov.uk>
License-File: LICENSE
Classifier: License :: OSI Approved :: MIT License
Classifier: Programming Language :: Python :: 3
Classifier: Topic :: Database
Requires-Python: >=3.7.11
Requires-Dist: apsw>=3.43.0.0
Requires-Dist: boto3>=1.18.51
Provides-Extra: dev
Requires-Dist: pytest-cov>=3.0.0; extra == 'dev'
Requires-Dist: pytest>=6.2.5; extra == 'dev'
